taichi_volume_renderer/__init__.py
taichi_volume_renderer/canvas.py
taichi_volume_renderer/io.py
taichi_volume_renderer/math.py
taichi_volume_renderer-1.6.0.dist-info/licenses/LICENSE
taichi_volume_renderer-1.6.0.dist-info/METADATA
taichi_volume_renderer-1.6.0.dist-info/WHEEL
taichi_volume_renderer-1.6.0.dist-info/top_level.txt
taichi_volume_renderer-1.6.0.dist-info/RECORD
