Metadata-Version: 2.4
Name: taichi-volume-renderer
Version: 1.6.0
Summary: A python package for real-time GPU volume rendering based on taichi
Home-page: https://github.com/ShengzhiWu/taichi-volume-renderer
Author: Shengzhi Wu
Author-email: e1124755@u.nus.edu
Keywords: taichi volume rendering 3d visualization gaussian splatting point cloud graphics
Classifier: Programming Language :: Python :: 3
Classifier: License :: OSI Approved :: MIT License
Classifier: Operating System :: OS Independent
Classifier: Topic :: Scientific/Engineering :: Visualization
License-File: LICENSE
Requires-Dist: numpy
Requires-Dist: taichi
Dynamic: author
Dynamic: author-email
Dynamic: classifier
Dynamic: description
Dynamic: description-content-type
Dynamic: home-page
Dynamic: keywords
Dynamic: license-file
Dynamic: requires-dist
Dynamic: summary
